notify_tls_client/__init__.py
notify_tls_client/core/__init__.py
notify_tls_client/core/client_identifiers_manager.py
notify_tls_client/core/notifytlsclient.py
notify_tls_client/core/client/__init__.py
notify_tls_client/core/client/decorators.py
notify_tls_client/core/proxiesmanager/__init__.py
notify_tls_client/core/proxiesmanager/proxiesmanager.py
notify_tls_client/core/proxiesmanager/proxiesmanagerloader.py
notify_tls_client/tls_client/__init__.py
notify_tls_client/tls_client/__version__.py
notify_tls_client/tls_client/cffi.py
notify_tls_client/tls_client/cookies.py
notify_tls_client/tls_client/exceptions.py
notify_tls_client/tls_client/response.py
notify_tls_client/tls_client/sessions.py
notify_tls_client/tls_client/settings.py
notify_tls_client/tls_client/structures.py
notify_tls_client/tls_client/dependencies/__init__.py
notify_tls_client/tls_client/dependencies/tls-client-darwin-amd64-1.12.0.dylib
notify_tls_client/tls_client/dependencies/tls-client-linux-arm64-1.12.0.so
notify_tls_client/tls_client/dependencies/tls-client-linux-ubuntu-amd64-1.12.0.so
notify_tls_client/tls_client/dependencies/tls-client-windows-64-1.12.0.dll
notify_tls_client-0.1.9.dist-info/METADATA
notify_tls_client-0.1.9.dist-info/WHEEL
notify_tls_client-0.1.9.dist-info/top_level.txt
notify_tls_client-0.1.9.dist-info/RECORD
