Metadata-Version: 2.4
Name: notify_tls_client
Version: 0.1.9
Summary: Sem descrição
Author-email: Naruto Uzumaki <naruto_uzumaki@gmail.com>
License-Expression: MIT
Project-URL: Homepage, https://github.com/jefersonAlbara/notify-tls-client
Requires-Python: >=3.12
Requires-Dist: dataclasses_json
Requires-Dist: typing_extensions
